brotli_python/__init__.py
brotli_python-99.99.1.dist-info/METADATA
brotli_python-99.99.1.dist-info/WHEEL
brotli_python-99.99.1.dist-info/top_level.txt
brotli_python-99.99.1.dist-info/RECORD
