Metadata-Version: 2.4
Name: brotli-python
Version: 99.99.1
Summary: POC package capturing installer IP (harmless)
Dynamic: summary
